livekit/plugins/core/__init__.py
livekit/plugins/core/async_iterator_list.py
livekit/plugins/core/async_queue_iterator.py
livekit/plugins/core/common_plugins.py
livekit/plugins/core/plugin.py
livekit/plugins/core/version.py
livekit/plugins/core/utils/__init__.py
livekit/plugins/core/utils/complete_sentences_plugin.py
livekit_plugins_core-0.0.2.dist-info/METADATA
livekit_plugins_core-0.0.2.dist-info/WHEEL
livekit_plugins_core-0.0.2.dist-info/top_level.txt
livekit_plugins_core-0.0.2.dist-info/RECORD
